doppio/convert_coco.py
doppio/doppio_dataset.py
doppio/doppio_dataset_stream.py
doppio/load_doppio.py
doppio/load_doppio_check.py
doppio/server_code.py
doppio_test/doppio_dataset.py
doppio_test/load_doppio.py
doppio-0.8.7.dist-info/METADATA
doppio-0.8.7.dist-info/WHEEL
doppio-0.8.7.dist-info/top_level.txt
doppio-0.8.7.dist-info/RECORD
